hwtLib/__init__.py
hwtLib/abstract/__init__.py
hwtLib/abstract/addressStepTranslation.py
hwtLib/abstract/busBridge.py
hwtLib/abstract/busEndpoint.py
hwtLib/abstract/busEndpoint_test.py
hwtLib/abstract/busInterconnect.py
hwtLib/abstract/busStaticRemap.py
hwtLib/abstract/componentBuilder.py
hwtLib/abstract/debug_bus_monitor.py
hwtLib/abstract/discoverAddressSpace.py
hwtLib/abstract/hwExceptionCtx.py
hwtLib/abstract/sim_ram.py
hwtLib/abstract/streamBuilder.py
hwtLib/abstract/template_configured.py
hwtLib/abstract/template_configured_test.py
hwtLib/abstract/frame_utils/__init__.py
hwtLib/abstract/frame_utils/alignment_utils.py
hwtLib/abstract/frame_utils/alignment_utils_test.py
hwtLib/abstract/frame_utils/byte_src_info.py
hwtLib/abstract/frame_utils/join/__init__.py
hwtLib/abstract/frame_utils/join/fsm.py
hwtLib/abstract/frame_utils/join/input_reg_val.py
hwtLib/abstract/frame_utils/join/state_trans_info.py
hwtLib/abstract/frame_utils/join/state_trans_item.py
hwtLib/abstract/frame_utils/join/state_trans_table.py
hwtLib/abstract/frame_utils/join/test.py
hwtLib/amba/__init__.py
hwtLib/amba/ace.py
hwtLib/amba/aceLite.py
hwtLib/amba/axi3.py
hwtLib/amba/axi3Lite.py
hwtLib/amba/axi4.py
hwtLib/amba/axi4Lite.py
hwtLib/amba/axi_intf_common.py
hwtLib/amba/axi_test.py
hwtLib/amba/axis.py
hwtLib/amba/axis_fullduplex.py
hwtLib/amba/constants.py
hwtLib/amba/axiLite_comp/__init__.py
hwtLib/amba/axiLite_comp/axi4Lite_withId.py
hwtLib/amba/axiLite_comp/buff_test.py
hwtLib/amba/axiLite_comp/endpoint.py
hwtLib/amba/axiLite_comp/endpoint_arr_test.py
hwtLib/amba/axiLite_comp/endpoint_fromInterfaces_test.py
hwtLib/amba/axiLite_comp/endpoint_struct_test.py
hwtLib/amba/axiLite_comp/endpoint_test.py
hwtLib/amba/axiLite_comp/to_axi.py
hwtLib/amba/axiLite_comp/to_axi_test.py
hwtLib/amba/axiLite_comp/sim/__init__.py
hwtLib/amba/axiLite_comp/sim/memSpaceMaster.py
hwtLib/amba/axiLite_comp/sim/ram.py
hwtLib/amba/axiLite_comp/sim/utils.py
hwtLib/amba/axi_comp/__init__.py
hwtLib/amba/axi_comp/buff.py
hwtLib-2.9.dist-info/LICENSE
hwtLib-2.9.dist-info/METADATA
hwtLib-2.9.dist-info/WHEEL
hwtLib-2.9.dist-info/top_level.txt
hwtLib-2.9.dist-info/RECORD
