Metadata-Version: 2.1
Name: hwtLib
Version: 2.9
Summary: library of hardware components and test for HWToolkit framework (hwt, FPGA devel. tools)
Home-page: https://github.com/Nic30/hwtLib
Author: Michal Orsak
Author-email: Nic30original@gmail.com
License: MIT
Platform: UNKNOWN
Classifier: Development Status :: 4 - Beta
Classifier: Intended Audience :: Developers
Classifier: License :: OSI Approved :: MIT License
Classifier: Operating System :: OS Independent
Classifier: Programming Language :: Python :: 3 :: Only
Classifier: Programming Language :: Python :: 3.6
Classifier: Programming Language :: Python :: 3.7
Classifier: Programming Language :: Python :: 3.8
Classifier: Programming Language :: Python :: 3.9
Classifier: Topic :: Scientific/Engineering :: Electronic Design Automation (EDA)
Classifier: Topic :: System :: Hardware
Classifier: Topic :: System :: Emulators
Classifier: Topic :: Utilities
License-File: LICENSE
Requires-Dist: hwt (>=3.8)
Requires-Dist: Pillow
